django_canvas_api_token-0.2.0.dist-info/DESCRIPTION.rst
django_canvas_api_token-0.2.0.dist-info/zip-safe
django_canvas_api_token-0.2.0.dist-info/top_level.txt
django_canvas_api_token-0.2.0.dist-info/metadata.json
django_canvas_api_token-0.2.0.dist-info/WHEEL
django_canvas_api_token-0.2.0.dist-info/RECORD
django_canvas_api_token-0.2.0.dist-info/METADATA
canvas_api_token/__init__.py
canvas_api_token/utils.py
canvas_api_token/models.py
canvas_api_token/decorators.py
canvas_api_token/urls.py
canvas_api_token/admin.py
canvas_api_token/views.py
canvas_api_token/migrations/__init__.py
canvas_api_token/migrations/0002_auto_20150430_1409.py
canvas_api_token/migrations/0001_initial.py
