Metadata-Version: 2.0
Name: django-canvas-api-token
Version: 0.2.0
Summary: Django app for generating Canvas API user oauth tokens
Home-page: https://github.com/harvard-dce/django-canvas-api-token
Author: Jay Luker
Author-email: jay_luker@harvard.edu
License: BSD
Platform: UNKNOWN
Classifier: Environment :: Web Environment
Classifier: Framework :: Django
Classifier: Intended Audience :: Developers
Classifier: License :: OSI Approved :: BSD License
Classifier: Operating System :: OS Independent
Classifier: Programming Language :: Python
Classifier: Programming Language :: Python :: 2.6
Classifier: Programming Language :: Python :: 2.7
Classifier: Topic :: Internet :: WWW/HTTP
Classifier: Topic :: Internet :: WWW/HTTP :: Dynamic Content
Classifier: Topic :: Education
Requires-Dist: Django (>=1.6)
Requires-Dist: requests
